fedmsg/__init__.py
fedmsg/config.py
fedmsg/core.py
fedmsg/utils.py
fedmsg/commands/__init__.py
fedmsg/commands/announce.py
fedmsg/commands/check.py
fedmsg/commands/collectd.py
fedmsg/commands/config.py
fedmsg/commands/gateway.py
fedmsg/commands/hub.py
fedmsg/commands/ircbot.py
fedmsg/commands/logger.py
fedmsg/commands/relay.py
fedmsg/commands/replay.py
fedmsg/commands/tail.py
fedmsg/commands/trigger.py
fedmsg/consumers/__init__.py
fedmsg/consumers/dummy.py
fedmsg/consumers/gateway.py
fedmsg/consumers/ircbot.py
fedmsg/consumers/relay.py
fedmsg/crypto/__init__.py
fedmsg/crypto/gpg.py
fedmsg/crypto/utils.py
fedmsg/crypto/x509.py
fedmsg/crypto/x509_ng.py
fedmsg/encoding/__init__.py
fedmsg/encoding/sqla.py
fedmsg/meta/__init__.py
fedmsg/meta/announce.py
fedmsg/meta/base.py
fedmsg/meta/default.py
fedmsg/meta/logger.py
fedmsg/replay/__init__.py
fedmsg/replay/sqlstore.py
fedmsg/tests/__init__.py
fedmsg/tests/base.py
fedmsg/tests/common.py
fedmsg/tests/fedmsg-test-config.py
fedmsg/tests/test_commands.py
fedmsg/tests/test_config.py
fedmsg/tests/test_core.py
fedmsg/tests/test_crypto_gpg.py
fedmsg/tests/test_crypto_switching.py
fedmsg/tests/test_hub.py
fedmsg/tests/test_meta.py
fedmsg/tests/test_replay.py
fedmsg/tests/test_threads.py
fedmsg/tests/test_utils.py
fedmsg/tests/test_certs/README
fedmsg/tests/test_certs/build-and-sign-key
fedmsg/tests/test_certs/build-ca
fedmsg/tests/test_certs/build-key
fedmsg/tests/test_certs/build-key-server
fedmsg/tests/test_certs/build-req
fedmsg/tests/test_certs/clean-all
fedmsg/tests/test_certs/list-crl
fedmsg/tests/test_certs/openssl-0.9.6.cnf
fedmsg/tests/test_certs/openssl-0.9.8.cnf
fedmsg/tests/test_certs/openssl-1.0.0.cnf
fedmsg/tests/test_certs/openssl-1.0.0.cnf-old-copy
fedmsg/tests/test_certs/pkitool
fedmsg/tests/test_certs/rebuild-all-fedmsg-certs
fedmsg/tests/test_certs/revoke-full
fedmsg/tests/test_certs/sign-req
fedmsg/tests/test_certs/vars
fedmsg/tests/test_certs/gpg/.gpg-v21-migrated
fedmsg/tests/test_certs/gpg/corrupt.sig
fedmsg-1.1.7.dist-info/LICENSE
fedmsg-1.1.7.dist-info/METADATA
fedmsg-1.1.7.dist-info/WHEEL
fedmsg-1.1.7.dist-info/entry_points.txt
fedmsg-1.1.7.dist-info/top_level.txt
fedmsg-1.1.7.dist-info/RECORD
